odoo/addons/sale_order_line_chained_move/README.rst
odoo/addons/sale_order_line_chained_move/__init__.py
odoo/addons/sale_order_line_chained_move/__manifest__.py
odoo/addons/sale_order_line_chained_move/hooks.py
odoo/addons/sale_order_line_chained_move/i18n/it.po
odoo/addons/sale_order_line_chained_move/i18n/sale_order_line_chained_move.pot
odoo/addons/sale_order_line_chained_move/models/__init__.py
odoo/addons/sale_order_line_chained_move/models/sale_order_line.py
odoo/addons/sale_order_line_chained_move/models/stock_move.py
odoo/addons/sale_order_line_chained_move/models/stock_rule.py
odoo/addons/sale_order_line_chained_move/readme/CONTRIBUTORS.md
odoo/addons/sale_order_line_chained_move/readme/DESCRIPTION.md
odoo/addons/sale_order_line_chained_move/readme/USAGE.md
odoo/addons/sale_order_line_chained_move/static/description/icon.png
odoo/addons/sale_order_line_chained_move/static/description/index.html
odoo/addons/sale_order_line_chained_move/tests/__init__.py
odoo/addons/sale_order_line_chained_move/tests/test_chained_move.py
odoo/addons/sale_order_line_chained_move/views/stock_rule_views.xml
odoo_addon_sale_order_line_chained_move-18.0.1.0.0.2.dist-info/METADATA
odoo_addon_sale_order_line_chained_move-18.0.1.0.0.2.dist-info/WHEEL
odoo_addon_sale_order_line_chained_move-18.0.1.0.0.2.dist-info/top_level.txt
odoo_addon_sale_order_line_chained_move-18.0.1.0.0.2.dist-info/RECORD
